lavender/__init__.py
lavender/lavender.py
lavender_logging-1.0.0.dist-info/METADATA
lavender_logging-1.0.0.dist-info/WHEEL
lavender_logging-1.0.0.dist-info/RECORD
