Metadata-Version: 2.1
Name: lavender-logging
Version: 1.0.0
Summary: An opinionated logger and configuration system.
Home-page: https://github.com/NimajnebEC/lavender-logging
License: MIT
Author: NimajnebEC
Author-email: nimajnebec@users.noreply.github.com
Requires-Python: >=3.8.1,<4.0.0
Classifier: License :: OSI Approved :: MIT License
Classifier: Programming Language :: Python :: 3
Classifier: Programming Language :: Python :: 3.9
Classifier: Programming Language :: Python :: 3.10
Classifier: Programming Language :: Python :: 3.11
Classifier: Programming Language :: Python :: 3.12
Project-URL: Repository, https://github.com/NimajnebEC/lavender-logging
